sentry_swift_nodestore/__init__.py
sentry_swift_nodestore/backend.py
sentry_swift_nodestore-1.0.3.dist-info/DESCRIPTION.rst
sentry_swift_nodestore-1.0.3.dist-info/METADATA
sentry_swift_nodestore-1.0.3.dist-info/RECORD
sentry_swift_nodestore-1.0.3.dist-info/WHEEL
sentry_swift_nodestore-1.0.3.dist-info/metadata.json
sentry_swift_nodestore-1.0.3.dist-info/top_level.txt
