Metadata-Version: 2.0
Name: sentry-swift-nodestore
Version: 1.0.3
Summary: A Sentry extension to add Swift as a NodeStore backend.
Home-page: https://gitlab.fs.eckler.ca/pcouto/sentry-swift-nodestore
Author: Phillip Couto
Author-email: pcouto@eckler.ca
License: BSD
Platform: UNKNOWN
Classifier: Framework :: Django
Classifier: Intended Audience :: Developers
Classifier: Intended Audience :: System Administrators
Classifier: Operating System :: OS Independent
Classifier: Topic :: Software Development
Requires-Dist: sentry (>=8.19.0)
Requires-Dist: python-swiftclient (>=3.5.0)
